kamoe/__init__.py
kamoe/grkan.py
kamoe/kamoe.py
kamoe-0.1.8.dist-info/METADATA
kamoe-0.1.8.dist-info/WHEEL
kamoe-0.1.8.dist-info/RECORD
