Metadata-Version: 2.1
Name: kamoe
Version: 0.1.8
Summary: Kolmogorov-Arnold Mixtures of Experts
Author: Rémi Genet
Requires-Python: >=3.9,<3.12
Classifier: Programming Language :: Python :: 3
Classifier: Programming Language :: Python :: 3.9
Classifier: Programming Language :: Python :: 3.10
Classifier: Programming Language :: Python :: 3.11
Requires-Dist: keras (>=3.0.0,<4.0)
Requires-Dist: keras_efficient_kan (>=0.1.4,<0.2.0)
